TFchirp/__init__.py
TFchirp-0.0.2.dist-info/LICENSE.txt
TFchirp-0.0.2.dist-info/METADATA
TFchirp-0.0.2.dist-info/WHEEL
TFchirp-0.0.2.dist-info/top_level.txt
TFchirp-0.0.2.dist-info/RECORD
