Metadata-Version: 2.1
Name: TFchirp
Version: 0.0.2
Summary: TFchirp: Time Frequency Decomposition Toolbox for Chirp Signals
Home-page: https://xli2522.github.io/TFchirp/
Author: Xiyuan Li
Author-email: xli2522@uwo.ca
License: GNU
Platform: UNKNOWN
Classifier: Natural Language :: English
Classifier: Programming Language :: Python :: 3
Classifier: License :: OSI Approved :: GNU General Public License v3 (GPLv3)
Classifier: Operating System :: OS Independent
Requires-Python: >=3.6
